AIPyS/DataLoad.py
AIPyS/__init__.py
AIPyS/draft.py
AIPyS/argarsescripts/__init__.py
AIPyS/argarsescripts/cellpose_granularity_video_gen.py
AIPyS/argarsescripts/cellpose_segment_video_gen.py
AIPyS/argarsescripts/precision_path_run.py
AIPyS/argarsescripts/set_parameters.py
AIPyS/argarsescripts/update_parameters.py
AIPyS/segmentation/__init__.py
AIPyS/segmentation/cellpose/AIPS_cellpose.py
AIPyS/segmentation/cellpose/AIPS_cellpse_video_gen.py
AIPyS/segmentation/cellpose/StackObjects_cellpose.py
AIPyS/segmentation/cellpose/__init__.py
AIPyS/segmentation/parametric/GlobalSeg.py
AIPyS/segmentation/parametric/ImageSeqGlobSeg.py
AIPyS/segmentation/parametric/__init__.py
AIPyS/supportFunctions/AIPS_file_display.py
AIPyS/supportFunctions/AIPS_functions.py
AIPyS/supportFunctions/AIPS_granularity.py
AIPyS/supportFunctions/AIPS_module.py
AIPyS/supportFunctions/AIPS_simulate.py
AIPyS/supportFunctions/Display_composit.py
AIPyS/supportFunctions/GranularityFunc.py
AIPyS/supportFunctions/Granularity_cellprofiler.py
AIPyS/supportFunctions/__init__.py
AIPyS/supportFunctions/display_and_xml.py
AIPyS/supportFunctions/unpack_h5.py
web_app/__init__.py
web_app/Image_labeling/__init__.py
web_app/Image_labeling/app.py
web_app/Image_labeling/draft.py
AIpYSPro-0.1.dist-info/METADATA
AIpYSPro-0.1.dist-info/WHEEL
AIpYSPro-0.1.dist-info/top_level.txt
AIpYSPro-0.1.dist-info/RECORD
