Metadata-Version: 2.1
Name: AIpYSPro
Version: 0.1
Summary: AI Powered Photoswitchable Screen
Home-page: 
Author: Gil Kanfer
Author-email: gil.kanfer.il@gmail.com
